.coveragerc
LICENSE
MANIFEST.in
README.rst
runtests.py
setup.cfg
setup.py
tox.ini
django_require_license.egg-info/PKG-INFO
django_require_license.egg-info/SOURCES.txt
django_require_license.egg-info/dependency_links.txt
django_require_license.egg-info/requires.txt
django_require_license.egg-info/top_level.txt
doc/Makefile
doc/conf.py
doc/development.rst
doc/index.rst
doc/make.bat
doc/tutorial.rst
require_license/__init__.py
require_license/storage.py
require_license/tests/__init__.py
require_license/tests/requirements.txt
require_license/tests/settings.py
require_license/tests/test_storage.py
require_license/tests/test_version.py
require_license/tests/resources/js/JS-LICENSE.txt
require_license/tests/resources/js/app.build.js
require_license/tests/resources/js/app.js
require_license/tests/resources/js/app/main.js
require_license/tests/resources/js/libs/almond.js
require_license/tests/resources/js/libs/jquery.min.js
require_license/tests/resources/js/libs/loglevel.js
require_license/tests/resources/js/libs/require.js