Metadata-Version: 1.1
Name: django-require-license
Version: 1.0.2
Summary: License header for django-require projects.
Home-page: https://github.com/collab-project/django-require-license
Author: Thijs Triemstra
Author-email: info@collab.nl
License: MIT
Keywords: django requirejs plugin require.js
Platform: UNKNOWN
Classifier: Development Status :: 5 - Production/Stable
Classifier: Environment :: Web Environment
Classifier: Framework :: Django
Classifier: Intended Audience :: Developers
Classifier: License :: OSI Approved :: MIT License
Classifier: Operating System :: OS Independent
Classifier: Programming Language :: Python
Classifier: Programming Language :: Python
Classifier: Programming Language :: Python :: 2
Classifier: Programming Language :: Python :: 2.7
Classifier: Programming Language :: Python :: 3
Classifier: Programming Language :: Python :: 3.4
